preprocessutils.py
preprocessutils-1.0.2.dist-info/LICENSE.txt
preprocessutils-1.0.2.dist-info/METADATA
preprocessutils-1.0.2.dist-info/WHEEL
preprocessutils-1.0.2.dist-info/top_level.txt
preprocessutils-1.0.2.dist-info/RECORD
