Metadata-Version: 2.1
Name: preprocessutils
Version: 1.0.2
Summary: UNKNOWN
Home-page: UNKNOWN
Author: Punit Nanda
Author-email: punit.nanda01@gmail.com
License: MIT
Platform: UNKNOWN
Classifier: License :: OSI Approved :: MIT License
Classifier: Programming Language :: Python :: 3
Classifier: Programming Language :: Python :: 3.7
Requires-Dist: imbalanced-learn
Requires-Dist: numpy
Requires-Dist: pandas
